[
    {
        "criterion": "gini",
        "min_impurity_decrease": 1e-10,
        "max_depth": 200
    },
    {
        "criterion": "log_loss",
        "min_impurity_decrease": 1e-08,
        "max_depth": 200
    },
    {
        "criterion": "gini",
        "min_impurity_decrease": 1e-08,
        "max_depth": 200
    },
    {
        "criterion": "gini",
        "min_impurity_decrease": 1e-08,
        "max_depth": 150
    },
    {
        "criterion": "log_loss",
        "min_impurity_decrease": 1e-10,
        "max_depth": null
    },
    {
        "criterion": "log_loss",
        "min_impurity_decrease": 0.0,
        "max_depth": 150
    },
    {
        "criterion": "log_loss",
        "min_impurity_decrease": 0.0,
        "max_depth": null
    },
    {
        "criterion": "gini",
        "min_impurity_decrease": 1e-10,
        "max_depth": 150
    },
    {
        "criterion": "log_loss",
        "min_impurity_decrease": 1e-12,
        "max_depth": 200
    },
    {
        "criterion": "gini",
        "min_impurity_decrease": 0.0,
        "max_depth": 200
    }
]